LICENSE
MANIFEST.in
README.md
setup.cfg
setup.py
xor_string/__init__.py
xor_string/xor_string.py
xor_string.egg-info/PKG-INFO
xor_string.egg-info/SOURCES.txt
xor_string.egg-info/dependency_links.txt
xor_string.egg-info/top_level.txt