Metadata-Version: 1.1
Name: xor-string
Version: 0.2.3
Summary: Elegant xor encryption in Python
Home-page: https://github.com/Akagi201/xor_string
Author: Akagi201
Author-email: akagi201@gmail.com
License: MIT
Download-URL: https://github.com/Akagi201/xor_string/tarball/0.2.3
Keywords: xor,string,itertools,python
Platform: UNKNOWN
Classifier: Development Status :: 3 - Alpha
Classifier: Environment :: Console
Classifier: Environment :: Console :: Curses
Classifier: Intended Audience :: Developers
Classifier: License :: OSI Approved :: MIT License
Classifier: Operating System :: POSIX :: Linux
Classifier: Programming Language :: Python
Classifier: Programming Language :: Python :: 2
Classifier: Programming Language :: Python :: 2.7
Classifier: Programming Language :: Python :: 3
Classifier: Programming Language :: Python :: 3.5
Classifier: Topic :: Security
Classifier: Topic :: System :: Networking
Classifier: Topic :: System :: Systems Administration
Classifier: Topic :: Utilities
